LICENSE
README.md
setup.py
rungalileo_tidecv.egg-info/PKG-INFO
rungalileo_tidecv.egg-info/SOURCES.txt
rungalileo_tidecv.egg-info/dependency_links.txt
rungalileo_tidecv.egg-info/requires.txt
rungalileo_tidecv.egg-info/top_level.txt
tidecv/__init__.py
tidecv/ap.py
tidecv/data.py
tidecv/datasets.py
tidecv/functions.py
tidecv/helpers.py
tidecv/plotting.py
tidecv/quantify.py
tidecv/errors/error.py
tidecv/errors/main_errors.py
tidecv/errors/qualifiers.py