Metadata-Version: 2.1
Name: rungalileo-tidecv
Version: 0.0.5
Summary: A General Toolbox for Identifying ObjectDetection Errors
Home-page: https://github.com/rungalileo/tide
Author: Galileo
Author-email: galileo@rungalileo.io
License: MIT
Platform: UNKNOWN
Classifier: License :: OSI Approved :: MIT License
Classifier: Programming Language :: Python :: 3
Classifier: Programming Language :: Python :: 3.6
Classifier: Operating System :: OS Independent
Requires-Python: >=3.6
License-File: LICENSE
